CHANGES.rst
LICENSE
MANIFEST.in
README.rst
setup.py
kpy/__init__.py
kpy/kpy.py
kpy.egg-info/PKG-INFO
kpy.egg-info/SOURCES.txt
kpy.egg-info/dependency_links.txt
kpy.egg-info/top_level.txt