Metadata-Version: 1.1
Name: kpy
Version: 0.2.2
Summary: mobile-phone's model name extractor from user agent
Home-page: https://github.com/ikegami-yukino/kpy
Author: Yukino Ikegami
Author-email: yukino0131@me.com
License: MIT License
Keywords: mobile-phone,smartphone,cell-phone,user agent
Platform: POSIX
Platform: Windows
Platform: Unix
Platform: MacOS
Classifier: Development Status :: 3 - Alpha
Classifier: Intended Audience :: Developers
Classifier: Intended Audience :: Information Technology
Classifier: License :: OSI Approved :: MIT License
Classifier: Operating System :: MacOS
Classifier: Operating System :: Microsoft
Classifier: Operating System :: POSIX
Classifier: Programming Language :: Python :: 2.6
Classifier: Programming Language :: Python :: 2.7
Classifier: Programming Language :: Python :: 3.3
Classifier: Programming Language :: Python :: 3.4
Classifier: Programming Language :: Python :: 3.5
